<?xml version="1.0"?>
<interval_containers type="scales"><interval_container type="scales"><name>Nahawand</name><akaName>Äolisch 7</akaName><akaName>H.M. I</akaName><akaName>Harmonisches Moll</akaName><akaName>Aeolian 7</akaName><akaName>Harmonic Minor</akaName><description></description><intervals><interval name="1" value="0"/><interval name="2" value="2"/><interval name="b3" value="3"/><interval name="4" value="5"/><interval name="5" value="7"/><interval name="b6" value="8"/><interval name="7" value="11"/></intervals></interval_container></interval_containers>