<?xml version="1.0"?>
<instruments><folder name="Portugiesische Gitarre"><instrument><name>Portugiesische Gitarre (6x2 Saiten) - Coimbra</name><description>aka: Portuguese Guitar, Gitarrera Portugesa, Gitarrera de Coimbra&#xd;
Herkunft: Portugal</description><stringCount>6</stringCount><scaleLength unit="mm" value="490.0"/><lefty_righty>false</lefty_righty><fretless>false</fretless><doubled_strings>true</doubled_strings><pitch><note level="3" octaveJump="false" stringNumber="1" value="9"/><note level="3" octaveJump="false" stringNumber="2" value="7"/><note level="3" octaveJump="false" stringNumber="3" value="2"/><note level="2" octaveJump="true" stringNumber="4" value="9"/><note level="2" octaveJump="true" stringNumber="5" value="7"/><note level="2" octaveJump="true" stringNumber="6" value="0"/></pitch><midiInstrumentNumber>24</midiInstrumentNumber><clef>5</clef></instrument><instrument><name>Portugiesische Gitarre (6x2 Saiten) - Lisbon</name><description>aka: Portuguese Guitar, Gitarrera Portugesa, Gitarrera de Lisboa&#xd;
Herkunft: Portugal</description><stringCount>6</stringCount><scaleLength unit="mm" value="460.0"/><lefty_righty>false</lefty_righty><fretless>false</fretless><doubled_strings>true</doubled_strings><pitch><note level="3" octaveJump="false" stringNumber="1" value="11"/><note level="3" octaveJump="false" stringNumber="2" value="9"/><note level="3" octaveJump="false" stringNumber="3" value="4"/><note level="2" octaveJump="true" stringNumber="4" value="11"/><note level="2" octaveJump="true" stringNumber="5" value="9"/><note level="2" octaveJump="true" stringNumber="6" value="2"/></pitch><midiInstrumentNumber>24</midiInstrumentNumber><clef>5</clef></instrument></folder></instruments>